setup.py
pysmarthome_lib/__init__.py
pysmarthome_lib/utils.py
pysmarthome_lib.egg-info/PKG-INFO
pysmarthome_lib.egg-info/SOURCES.txt
pysmarthome_lib.egg-info/dependency_links.txt
pysmarthome_lib.egg-info/not-zip-safe
pysmarthome_lib.egg-info/requires.txt
pysmarthome_lib.egg-info/top_level.txt
pysmarthome_lib/controllers/__init__.py
pysmarthome_lib/controllers/device_controller.py
pysmarthome_lib/controllers/plugin_controller.py
pysmarthome_lib/controllers/rgb_lamp_controller.py
pysmarthome_lib/managers/__init__.py
pysmarthome_lib/managers/manager.py
pysmarthome_lib/models/__init__.py
pysmarthome_lib/models/device_model.py
pysmarthome_lib/models/plugins_model.py
pysmarthome_lib/models/refs_model.py
pysmarthome_lib/models/rgb_light_model.py