Metadata-Version: 2.1
Name: pysmarthome-lib
Version: 0.1.5
Summary: A python lib that abstracts pysmarthome entities
Home-page: https://github.com/filipealvesdef/pysmarthome/tree/master/pysmarthome-lib
Author: Filipe Alves
Author-email: filipe.alvesdefernando@gmail.com
License: UNKNOWN
Platform: UNKNOWN
